CHANGELOG
MANIFEST.in
README.txt
setup.py
ielectric/__init__.py
ielectric.fab.egg-info/PKG-INFO
ielectric.fab.egg-info/SOURCES.txt
ielectric.fab.egg-info/dependency_links.txt
ielectric.fab.egg-info/entry_points.txt
ielectric.fab.egg-info/namespace_packages.txt
ielectric.fab.egg-info/not-zip-safe
ielectric.fab.egg-info/requires.txt
ielectric.fab.egg-info/top_level.txt
ielectric/fab/__init__.py