Metadata-Version: 1.0
Name: ielectric.fab
Version: 0.1.3
Summary: Personal fabric file
Home-page: http://www.fubar.si
Author: UNKNOWN
Author-email: UNKNOWN
License: GPL
Platform: UNKNOWN
Classifier: Programming Language :: Python
